factorial_aio_99/__init__.py
factorial_aio_99/app_streamlit.py
factorial_aio_99/factorial.py
factorial_aio_99-0.1.0.dist-info/METADATA
factorial_aio_99-0.1.0.dist-info/WHEEL
factorial_aio_99-0.1.0.dist-info/RECORD
