Metadata-Version: 2.1
Name: factorial-aio-99
Version: 0.1.0
Summary: 
Author: Your Name
Author-email: you@example.com
Requires-Python: >=3.12,<4.0
Classifier: Programming Language :: Python :: 3
Classifier: Programming Language :: Python :: 3.12
Requires-Dist: streamlit (>=1.34.0,<2.0.0)
